noisedestroyer.py
noisedestroyer-0.0.4.dist-info/LICENSE.txt
noisedestroyer-0.0.4.dist-info/METADATA
noisedestroyer-0.0.4.dist-info/WHEEL
noisedestroyer-0.0.4.dist-info/top_level.txt
noisedestroyer-0.0.4.dist-info/RECORD
