Metadata-Version: 2.1
Name: noisedestroyer
Version: 0.0.4
Summary: Remove background noise from your video and audio files quickly
Requires-Python: >=3.7
License-File: LICENSE.txt
Requires-Dist: httpx
Requires-Dist: aiofiles
Requires-Dist: aiohttp ~=3.9.1
